mediawikiapi/__init__.py
mediawikiapi/config.py
mediawikiapi/exceptions.py
mediawikiapi/language.py
mediawikiapi/mediawikiapi.py
mediawikiapi/requestsession.py
mediawikiapi/util.py
mediawikiapi/wikipediapage.py
mediawikiapi-1.2.dist-info/LICENSE
mediawikiapi-1.2.dist-info/METADATA
mediawikiapi-1.2.dist-info/WHEEL
mediawikiapi-1.2.dist-info/RECORD
