Metadata-Version: 2.1
Name: mediawikiapi
Version: 1.2
Summary: Wikipedia API on Python
License: MIT
Author: Taras Lehinevych
Author-email: info@taraslehinevych.me
Requires-Python: >=3.7,<4.0
Classifier: License :: OSI Approved :: MIT License
Classifier: Programming Language :: Python :: 3
Classifier: Programming Language :: Python :: 3.7
Classifier: Programming Language :: Python :: 3.8
Classifier: Programming Language :: Python :: 3.9
Classifier: Programming Language :: Python :: 3.10
Classifier: Programming Language :: Python :: 3.11
Requires-Dist: beautifulsoup4 (>=4.11.1,<5.0.0)
Requires-Dist: requests (>=2.28.1,<3.0.0)
